{
  "task": "level3_0166_0",
  "status": "error",
  "object": "12_pen_0",
  "target": "12_pen_0",
  "position_delta_cm": 11.554959146825018,
  "max_speed_mps": 0.05777479573412507,
  "events": [
    {
      "time": 0.0,
      "segment": 0,
      "kind": "physx_gripper_contact",
      "severity": "error",
      "message": "gripper contacts 2_lamp_0",
      "count": 121,
      "first_time": 0.0,
      "last_time": 2.0
    },
    {
      "time": 2.017,
      "segment": 1,
      "kind": "physx_gripper_contact",
      "severity": "error",
      "message": "gripper contacts 2_lamp_0",
      "count": 120,
      "first_time": 2.017,
      "last_time": 4.0
    },
    {
      "time": 4.017,
      "segment": 2,
      "kind": "physx_carried_object_contact",
      "severity": "error",
      "message": "12_pen_0 contacts 2_lamp_0",
      "count": 120,
      "first_time": 4.017,
      "last_time": 6.0
    },
    {
      "time": 4.017,
      "segment": 2,
      "kind": "physx_gripper_contact",
      "severity": "error",
      "message": "gripper contacts 2_lamp_0",
      "count": 120,
      "first_time": 4.017,
      "last_time": 6.0
    },
    {
      "time": 4.033,
      "segment": 2,
      "kind": "physx_carried_object_contact",
      "severity": "error",
      "message": "12_pen_0 contacts 10_pen_holder_0",
      "count": 119,
      "first_time": 4.033,
      "last_time": 6.0
    },
    {
      "time": 4.533,
      "segment": 2,
      "kind": "physx_gripper_contact",
      "severity": "error",
      "message": "gripper contacts 10_pen_holder_0",
      "count": 89,
      "first_time": 4.533,
      "last_time": 6.0
    },
    {
      "time": 6.017,
      "segment": 3,
      "kind": "physx_carried_object_contact",
      "severity": "error",
      "message": "12_pen_0 contacts 10_pen_holder_0",
      "count": 120,
      "first_time": 6.017,
      "last_time": 8.0
    },
    {
      "time": 6.017,
      "segment": 3,
      "kind": "physx_gripper_contact",
      "severity": "error",
      "message": "gripper contacts 10_pen_holder_0",
      "count": 120,
      "first_time": 6.017,
      "last_time": 8.0
    },
    {
      "time": 6.017,
      "segment": 3,
      "kind": "physx_carried_object_contact",
      "severity": "error",
      "message": "12_pen_0 contacts 2_lamp_0",
      "count": 120,
      "first_time": 6.017,
      "last_time": 8.0
    },
    {
      "time": 6.017,
      "segment": 3,
      "kind": "physx_gripper_contact",
      "severity": "error",
      "message": "gripper contacts 2_lamp_0",
      "count": 120,
      "first_time": 6.017,
      "last_time": 8.0
    },
    {
      "time": 8.017,
      "segment": 4,
      "kind": "physx_carried_object_contact",
      "severity": "error",
      "message": "12_pen_0 contacts 10_pen_holder_0",
      "count": 120,
      "first_time": 8.017,
      "last_time": 10.0
    },
    {
      "time": 8.017,
      "segment": 4,
      "kind": "physx_gripper_contact",
      "severity": "error",
      "message": "gripper contacts 10_pen_holder_0",
      "count": 120,
      "first_time": 8.017,
      "last_time": 10.0
    },
    {
      "time": 8.017,
      "segment": 4,
      "kind": "physx_carried_object_contact",
      "severity": "error",
      "message": "12_pen_0 contacts 2_lamp_0",
      "count": 120,
      "first_time": 8.017,
      "last_time": 10.0
    },
    {
      "time": 8.017,
      "segment": 4,
      "kind": "physx_gripper_contact",
      "severity": "error",
      "message": "gripper contacts 2_lamp_0",
      "count": 120,
      "first_time": 8.017,
      "last_time": 10.0
    }
  ]
}
